pandasdb2/__init__.py
pandasdb2/cache.py
pandasdb2/column.py
pandasdb2/connection.py
pandasdb2/exceptions.py
pandasdb2/expression.py
pandasdb2/table.py
pandasdb2/utils.py
pandasdb2-2.0.4.dist-info/LICENSE
pandasdb2-2.0.4.dist-info/METADATA
pandasdb2-2.0.4.dist-info/WHEEL
pandasdb2-2.0.4.dist-info/RECORD
