Metadata-Version: 2.1
Name: pandasdb2
Version: 2.0.4
Summary: Pandas but without bringing the data into memory
Home-page: https://github.com/shner-elmo/db-wrapper
License: MIT
Keywords: pandas,pandasdb,SQL
Author: Shneor Elmaleh
Author-email: 770elmo@gmail.com
Requires-Python: >=3.8
Classifier: Environment :: Console
Classifier: License :: OSI Approved :: MIT License
Classifier: Operating System :: OS Independent
Classifier: Programming Language :: Python
Classifier: Programming Language :: Python :: 3
Classifier: Programming Language :: Python :: 3.8
Classifier: Programming Language :: Python :: 3.9
Classifier: Programming Language :: Python :: 3.10
Classifier: Programming Language :: Python :: 3.11
Classifier: Programming Language :: Python :: 3
Classifier: Programming Language :: Python :: 3 :: Only
Classifier: Programming Language :: SQL
Classifier: Topic :: Database
Requires-Dist: pandas (>=1.5.2,<2.0.0)
Requires-Dist: pympler (>=1.0.1,<2.0.0)
Project-URL: Documentation, https://github.com/shner-elmo/pandas-db/blob/master/README.md
Project-URL: Repository, https://github.com/shner-elmo/db-wrapper
Project-URL: issues, https://github.com/shner-elmo/pandas-db/issues
